smartusbhub.py
smartusbhub-1.0.1.dist-info/licenses/LICENSE
smartusbhub-1.0.1.dist-info/METADATA
smartusbhub-1.0.1.dist-info/WHEEL
smartusbhub-1.0.1.dist-info/top_level.txt
smartusbhub-1.0.1.dist-info/RECORD
