Metadata-Version: 2.4
Name: smartusbhub
Version: 1.0.1
Summary: A Python library for SmartUSBHub that provides per-port power and data control, voltage and current monitoring, and manual plug/unplug simulation—designed for development, testing, and device management.
Author-email: Jasonzhang <embeddedtec@outlook.com>
License-Expression: Apache-2.0
Project-URL: Homepage, https://github.com/MrzhangF1ghter/smartusbhub
Project-URL: Issues, https://github.com/MrzhangF1ghter/smartusbhub/issues
Classifier: Programming Language :: Python :: 3
Classifier: Operating System :: OS Independent
Requires-Python: >=3.9
License-File: LICENSE
Requires-Dist: colorlog
Requires-Dist: numpy
Requires-Dist: pyserial
Dynamic: license-file
